{
  "pier": "30A",
  "loc": {
    "lon": "",
    "lat": "",
    "geohash": ""
  },
  "property": {
    "association": "Covenant Harbor Bible Camp",
    "established": "",
    "address": {
      "street": "",
      "city": "Lake Geneva",
      "state": "WI",
      "zip": ""
    }
  },
  "owners": [
    {
      "estateName": "",
      "member": false,
      "membershipType": "",
      "members": [
        { "t": "", "f": "Covenant Harbor Bible Camp", "m": "", "l": "", "s": "" }
      ]
    }
  ]
}
