{
  "pier": "872",
  "loc": {
    "lon": "",
    "lat": "",
    "geohash": ""
  },
  "property": {
    "association": "Syverstad",
    "established": "1955",
    "address": {
      "street": "",
      "city": "Lake Geneva",
      "state": "WI",
      "zip": ""
    }
  },
  "owners": [
    {
      "estateName": "",
      "member": false,
      "membershipType": "",
      "members": [
        { "t": "", "f": "Donald", "m": "F", "l": "Pike", "s": "" },
        { "t": "", "f": "Wendy", "m": "", "l": "Pike", "s": "" }
      ]
    }
  ]
}
