{
  "pier": "586",
  "loc": {
    "lon": "",
    "lat": "",
    "geohash": ""
  },
  "property": {
    "association": "Estates of Black Point",
    "established": "1888",
    "address": {
      "street": "",
      "city": "Linn",
      "state": "WI",
      "zip": ""
    }
  },
  "owners": [
    {
      "estateName": "",
      "member": false,
      "membershipType": "Residential Non-member",
      "members": [
        { "t": "", "f": "Steve", "m": "", "l": "Poulos", "s": "" }
      ]
    }
  ]
}
