{
  "pier": "350A",
  "loc": {
    "lon": "",
    "lat": "",
    "geohash": ""
  },
  "property": {
    "association": "George Williams College of Aurora University",
    "established": "1886",
    "address": {
      "street": "",
      "city": "Williams Bay",
      "state": "WI",
      "zip": ""
    }
  },
  "owners": [
    {
      "estateName": "",
      "member": false,
      "membershipType": "Residential Non-member",
      "members": [
        { "t": "", "f": "George Williams College Boat Dock", "m": "", "l": "", "s": "" }
      ]
    }
  ]
}
